<?xml version="1.0" encoding="UTF-8"?>
<con:resource name="/pet/{petId}/uploadImage" path="/pet/{petId}/uploadImage" id="a7840629-5c98-45c3-bdfb-a4a0ac4e1635" xmlns:xsi="http://www.w3.org/2001/XMLSchema-instance" xmlns:con="http://eviware.com/soapui/config">
  <con:settings>
    <con:setting id="a7840629-5c98-45c3-bdfb-a4a0ac4e1635fileName">%2Fpet%2F%7BpetId%7D%2FuploadImage</con:setting>
  </con:settings>
  <con:parameters>
    <con:parameter required="true">
      <con:name>petId</con:name>
      <con:style>TEMPLATE</con:style>
      <con:dataType>integer</con:dataType>
      <con:description>ID of pet to update</con:description>
    </con:parameter>
  </con:parameters>
  <con:method name="uploadFile" id="25386b29-db86-48f7-8458-e7a924fadbec" method="POST">
    <con:description>uploads an image</con:description>
    <con:settings/>
    <con:parameters>
      <con:parameter>
        <con:name>additionalMetadata</con:name>
        <con:style>QUERY</con:style>
        <con:description>Additional data to pass to server</con:description>
      </con:parameter>
      <con:parameter>
        <con:name>file</con:name>
        <con:style>QUERY</con:style>
        <con:description>file to upload</con:description>
      </con:parameter>
    </con:parameters>
    <con:representation type="RESPONSE">
      <con:mediaType>application/json</con:mediaType>
      <con:status>200</con:status>
      <con:params/>
      <con:sampleContent>{
  "code" : 0,
  "type" : "string",
  "message" : "string"
}</con:sampleContent>
    </con:representation>
    <con:representation type="REQUEST">
      <con:mediaType>multipart/form-data</con:mediaType>
      <con:params/>
    </con:representation>
    <con:request name="Request 1" id="3f8322d9-6b43-4e14-a7b0-170396d15716" mediaType="application/json">
      <con:settings/>
      <con:endpoint>http://petstore.swagger.io</con:endpoint>
      <con:credentials>
        <con:selectedAuthProfile>No Authorization</con:selectedAuthProfile>
        <con:authType>No Authorization</con:authType>
      </con:credentials>
      <con:parameters/>
    </con:request>
  </con:method>
</con:resource>
