<?xml version="1.0" encoding="UTF-8"?>
<con:resource name="/pet/{petId}" path="/pet/{petId}" id="375ae925-2ff1-4541-8eb2-2c9bc6b24095" xmlns:xsi="http://www.w3.org/2001/XMLSchema-instance" xmlns:con="http://eviware.com/soapui/config">
  <con:settings>
    <con:setting id="375ae925-2ff1-4541-8eb2-2c9bc6b24095fileName">%2Fpet%2F%7BpetId%7D</con:setting>
  </con:settings>
  <con:parameters>
    <con:parameter required="true">
      <con:name>petId</con:name>
      <con:style>TEMPLATE</con:style>
      <con:dataType>integer</con:dataType>
      <con:description>Pet id to delete</con:description>
    </con:parameter>
  </con:parameters>
  <con:method name="getPetById" id="a3763879-4fff-4b58-9d83-0ee6b933749e" method="GET">
    <con:description>Returns a single pet
Find pet by ID</con:description>
    <con:settings/>
    <con:parameters/>
    <con:representation type="RESPONSE">
      <con:mediaType>application/xml</con:mediaType>
      <con:status>200</con:status>
      <con:params/>
      <con:sampleContent><![CDATA[<Pet>
   <id>0</id>
   <Category>
      <id>0</id>
      <name>string</name>
   </Category>
   <name>doggie</name>
   <photoUrl>
      <photoUrls>string</photoUrls>
   </photoUrl>
   <tag>
      <Tag>
         <id>0</id>
         <name>string</name>
      </Tag>
   </tag>
   <status>available</status>
</Pet>]]></con:sampleContent>
    </con:representation>
    <con:representation type="RESPONSE">
      <con:mediaType>application/json</con:mediaType>
      <con:status>200</con:status>
      <con:params/>
      <con:sampleContent>{
  "id" : 0,
  "category" : {
    "id" : 0,
    "name" : "string"
  },
  "name" : "doggie",
  "photoUrls" : [ "string" ],
  "tags" : [ {
    "id" : 0,
    "name" : "string"
  } ],
  "status" : "available"
}</con:sampleContent>
    </con:representation>
    <con:representation type="RESPONSE">
      <con:mediaType>application/xml</con:mediaType>
      <con:status>400</con:status>
      <con:params/>
    </con:representation>
    <con:representation type="RESPONSE">
      <con:mediaType>application/json</con:mediaType>
      <con:status>400</con:status>
      <con:params/>
    </con:representation>
    <con:representation type="RESPONSE">
      <con:mediaType>application/xml</con:mediaType>
      <con:status>404</con:status>
      <con:params/>
    </con:representation>
    <con:representation type="RESPONSE">
      <con:mediaType>application/json</con:mediaType>
      <con:status>404</con:status>
      <con:params/>
    </con:representation>
    <con:request name="Request 1" id="29efdb60-4aae-4282-a885-dffa95505e3e" mediaType="application/json">
      <con:settings>
        <con:setting id="com.eviware.soapui.impl.wsdl.WsdlRequest@request-headers">&lt;xml-fragment/></con:setting>
      </con:settings>
      <con:endpoint>http://petstore.swagger.io</con:endpoint>
      <con:request/>
      <con:originalUri>http://petstore.swagger.io/v2/pet/1</con:originalUri>
      <con:credentials>
        <con:selectedAuthProfile>No Authorization</con:selectedAuthProfile>
        <con:authType>No Authorization</con:authType>
      </con:credentials>
      <con:jmsConfig JMSDeliveryMode="PERSISTENT"/>
      <con:parameters>
        <con:entry key="petId" value="1"/>
      </con:parameters>
    </con:request>
  </con:method>
  <con:method name="updatePetWithForm" id="67748225-38b3-4ede-a6b7-c654c8eec94a" method="POST">
    <con:description>Updates a pet in the store with form data</con:description>
    <con:settings/>
    <con:parameters>
      <con:parameter>
        <con:name>name</con:name>
        <con:style>QUERY</con:style>
        <con:description>Updated name of the pet</con:description>
      </con:parameter>
      <con:parameter>
        <con:name>status</con:name>
        <con:style>QUERY</con:style>
        <con:description>Updated status of the pet</con:description>
      </con:parameter>
    </con:parameters>
    <con:representation type="RESPONSE">
      <con:mediaType>application/xml</con:mediaType>
      <con:status>405</con:status>
      <con:params/>
    </con:representation>
    <con:representation type="RESPONSE">
      <con:mediaType>application/json</con:mediaType>
      <con:status>405</con:status>
      <con:params/>
    </con:representation>
    <con:representation type="REQUEST">
      <con:mediaType>application/x-www-form-urlencoded</con:mediaType>
      <con:params/>
    </con:representation>
    <con:request name="Request 1" id="316c07ad-c0fc-4289-901d-24d04960fcd0" mediaType="application/json">
      <con:settings/>
      <con:endpoint>http://petstore.swagger.io</con:endpoint>
      <con:credentials>
        <con:selectedAuthProfile>No Authorization</con:selectedAuthProfile>
        <con:authType>No Authorization</con:authType>
      </con:credentials>
      <con:parameters/>
    </con:request>
  </con:method>
  <con:method name="deletePet" id="68e43b3b-9b4e-4213-af7e-423a20b3c356" method="DELETE">
    <con:description>Deletes a pet</con:description>
    <con:settings/>
    <con:parameters>
      <con:parameter>
        <con:name>api_key</con:name>
        <con:style>HEADER</con:style>
        <con:description xsi:nil="true"/>
      </con:parameter>
    </con:parameters>
    <con:representation type="RESPONSE">
      <con:mediaType>application/xml</con:mediaType>
      <con:status>400</con:status>
      <con:params/>
    </con:representation>
    <con:representation type="RESPONSE">
      <con:mediaType>application/json</con:mediaType>
      <con:status>400</con:status>
      <con:params/>
    </con:representation>
    <con:representation type="RESPONSE">
      <con:mediaType>application/xml</con:mediaType>
      <con:status>404</con:status>
      <con:params/>
    </con:representation>
    <con:representation type="RESPONSE">
      <con:mediaType>application/json</con:mediaType>
      <con:status>404</con:status>
      <con:params/>
    </con:representation>
    <con:request name="Request 1" id="5a64a5d6-fe4a-436a-8ef4-1f1ba10415f6" mediaType="application/json">
      <con:settings/>
      <con:endpoint>http://petstore.swagger.io</con:endpoint>
      <con:credentials>
        <con:selectedAuthProfile>No Authorization</con:selectedAuthProfile>
        <con:authType>No Authorization</con:authType>
      </con:credentials>
      <con:parameters/>
    </con:request>
  </con:method>
</con:resource>
